cmem_plugin_loopwf/__init__.py
cmem_plugin_loopwf/exceptions.py
cmem_plugin_loopwf/loopwf.svg
cmem_plugin_loopwf/task.py
cmem_plugin_loopwf/workflow_type.py
cmem_plugin_loopwf-0.9.0.dist-info/METADATA
cmem_plugin_loopwf-0.9.0.dist-info/WHEEL
cmem_plugin_loopwf-0.9.0.dist-info/licenses/LICENSE
cmem_plugin_loopwf-0.9.0.dist-info/RECORD
