Metadata-Version: 2.4
Name: cmem-plugin-loopwf
Version: 0.9.0
Summary: Loop over the output of a task and start a sub-workflow for each entity.
License: Apache-2.0
License-File: LICENSE
Keywords: eccenca Corporate Memory,plugin
Author: eccenca GmbH
Author-email: cmempy-developer@eccenca.com
Requires-Python: >=3.13,<4.0
Classifier: Development Status :: 4 - Beta
Classifier: Environment :: Plugins
Classifier: License :: OSI Approved :: Apache Software License
Classifier: Programming Language :: Python :: 3
Classifier: Programming Language :: Python :: 3.13
Classifier: Programming Language :: Python :: 3.14
Requires-Dist: cmem-cmempy (>=24.2.0)
Requires-Dist: cmem-plugin-base (>=4.14.0,<5.0.0)
Requires-Dist: requests (>=2.0.1)
Project-URL: Homepage, https://github.com/eccenca/cmem-plugin-loopwf
